{"commitInfo":{"timestamp":1771780818205,"operation":"WRITE","operationParameters":{"mode":"Overwrite","partitionBy":"[]"},"readVersion":3,"isolationLevel":"Serializable","isBlindAppend":false,"operationMetrics":{"numFiles":"6","numRemovedFiles":"1","numRemovedBytes":"977","numOutputRows":"5","numOutputBytes":"5355"},"engineInfo":"Apache-Spark/4.1.1 Delta-Lake/4.1.0","txnId":"0c29e7f7-0d3f-419a-8ef4-fc2e804d2305"}}
{"add":{"path":"part-00001-bc5d54ec-aff0-4cd3-8b00-d5689db7de94-c000.snappy.parquet","partitionValues":{},"size":976,"modificationTime":1771780817081,"dataChange":true,"stats":"{\"numRecords\":1,\"minValues\":{\"id\":1,\"categoria\":\"A\",\"quantita\":10},\"maxValues\":{\"id\":1,\"categoria\":\"A\",\"quantita\":10},\"nullCount\":{\"id\":0,\"categoria\":0,\"quantita\":0}}"}}
{"add":{"path":"part-00003-99c0aeb4-26d1-4d26-8c27-b30d5371af85-c000.snappy.parquet","partitionValues":{},"size":977,"modificationTime":1771780817080,"dataChange":true,"stats":"{\"numRecords\":1,\"minValues\":{\"id\":2,\"categoria\":\"B\",\"quantita\":20},\"maxValues\":{\"id\":2,\"categoria\":\"B\",\"quantita\":20},\"nullCount\":{\"id\":0,\"categoria\":0,\"quantita\":0}}"}}
{"add":{"path":"part-00004-7c533a61-36e5-4194-a639-8a0d667bf485-c000.snappy.parquet","partitionValues":{},"size":977,"modificationTime":1771780817081,"dataChange":true,"stats":"{\"numRecords\":1,\"minValues\":{\"id\":3,\"categoria\":\"C\",\"quantita\":15},\"maxValues\":{\"id\":3,\"categoria\":\"C\",\"quantita\":15},\"nullCount\":{\"id\":0,\"categoria\":0,\"quantita\":0}}"}}
{"add":{"path":"part-00006-cefc7c3e-1e62-4632-ba81-776748d21695-c000.snappy.parquet","partitionValues":{},"size":977,"modificationTime":1771780817079,"dataChange":true,"stats":"{\"numRecords\":1,\"minValues\":{\"id\":4,\"categoria\":\"A\",\"quantita\":5},\"maxValues\":{\"id\":4,\"categoria\":\"A\",\"quantita\":5},\"nullCount\":{\"id\":0,\"categoria\":0,\"quantita\":0}}"}}
{"add":{"path":"part-00007-cb59227b-2fd4-4c80-b089-814b137f1c88-c000.snappy.parquet","partitionValues":{},"size":977,"modificationTime":1771780817080,"dataChange":true,"stats":"{\"numRecords\":1,\"minValues\":{\"id\":5,\"categoria\":\"B\",\"quantita\":25},\"maxValues\":{\"id\":5,\"categoria\":\"B\",\"quantita\":25},\"nullCount\":{\"id\":0,\"categoria\":0,\"quantita\":0}}"}}
{"remove":{"path":"part-00000-e85a9761-deb9-4a71-9179-d24ac4dd4cb3-c000.snappy.parquet","deletionTimestamp":1771780818142,"dataChange":true,"extendedFileMetadata":true,"partitionValues":{},"size":977}}
